deduplidog/__init__.py
deduplidog/__main__.py
deduplidog/deduplidog.py
deduplidog/helpers.py
deduplidog/utils.py
deduplidog-0.7.2.dist-info/LICENSE
deduplidog-0.7.2.dist-info/METADATA
deduplidog-0.7.2.dist-info/WHEEL
deduplidog-0.7.2.dist-info/entry_points.txt
deduplidog-0.7.2.dist-info/RECORD
