Metadata-Version: 2.3
Name: deduplidog
Version: 0.7.2
Summary: Yet another file deduplicator
License: GPL-3.0-or-later
Author: Edvard Rejthar
Author-email: edvard.rejthar@nic.cz
Requires-Python: >=3.11
Classifier: License :: OSI Approved :: GNU General Public License v3 or later (GPLv3+)
Classifier: Programming Language :: Python :: 3
Classifier: Programming Language :: Python :: 3.11
Classifier: Programming Language :: Python :: 3.12
Classifier: Programming Language :: Python :: 3.13
Requires-Dist: IPython
Requires-Dist: Pillow
Requires-Dist: humanize
Requires-Dist: imagehash
Requires-Dist: ipywidgets
Requires-Dist: mininterface[basic] (>=1,<2)
Requires-Dist: opencv-python
Requires-Dist: pillow-heif
Requires-Dist: sh
Requires-Dist: tqdm
Project-URL: Homepage, https://github.com/CZ-NIC/deduplidog
